downly/__init__.py
downly/download.py
downly/downly.py
downly-0.3.1.dist-info/licenses/LICENSE
downly-0.3.1.dist-info/METADATA
downly-0.3.1.dist-info/WHEEL
downly-0.3.1.dist-info/entry_points.txt
downly-0.3.1.dist-info/top_level.txt
downly-0.3.1.dist-info/RECORD
