Metadata-Version: 2.4
Name: downly
Version: 0.3.1
Summary: Yet another download manager in python.
Project-URL: Homepage, https://github.com/Amir-Hossein-ID/Downly
Keywords: download,url,fast,download manager
Classifier: Programming Language :: Python
Classifier: Programming Language :: Python :: 3
Requires-Python: >=3.9
License-File: LICENSE
Requires-Dist: aiohttp>=3.11.0
Requires-Dist: aiofiles>=24.1.0
Requires-Dist: rich>=14.0.0
Dynamic: license-file
